hytato/__init__.py
hytato/hytato.py
hytato-0.3.dist-info/LICENSE
hytato-0.3.dist-info/METADATA
hytato-0.3.dist-info/WHEEL
hytato-0.3.dist-info/top_level.txt
hytato-0.3.dist-info/RECORD
